setup.py
gas/__init__.py
gas/__main__.py
gas/authorize.py
gas/base.py
gas/deploy.py
gas.egg-info/PKG-INFO
gas.egg-info/SOURCES.txt
gas.egg-info/dependency_links.txt
gas.egg-info/entry_points.txt
gas.egg-info/not-zip-safe
gas.egg-info/requires.txt
gas.egg-info/top_level.txt