Metadata-Version: 1.0
Name: gas
Version: 0.0.1
Summary: A Google Apps Add-on for Google Docs Spreadsheets that loads items from the API into a sheet.
Home-page: https://github.com/joestump/python-gas-cli
Author: Joseph C. Stump
Author-email: joe@stu.mp
License: BSD
Keywords: google
Platform: UNKNOWN
